StatAssist/__init__.py
StatAssist/algebra.py
StatAssist/stats.py
StatAssist/utils.py
StatAssist-1.0.6.dist-info/METADATA
StatAssist-1.0.6.dist-info/WHEEL
StatAssist-1.0.6.dist-info/top_level.txt
StatAssist-1.0.6.dist-info/RECORD
