Metadata-Version: 2.1
Name: StatAssist
Version: 1.0.6
Summary: Math tools for private or personal use.
Author: Damion J. Quintanilla
Author-email: djq314159@gmail.com
License: MIT
Classifier: Programming Language :: Python :: 3
Classifier: License :: OSI Approved :: MIT License
Classifier: Operating System :: OS Independent
Requires-Dist: torch >=2.3.0
Requires-Dist: pandas >=2.2.2
Requires-Dist: scikit-learn >=1.4.2
Requires-Dist: openpyxl >=3.1.2
